twgw_controller/__init__.py
twgw_controller/api_service.py
twgw_controller/db_manager.py
twgw_controller/gateway.py
twgw_controller-2.1.data/data/twgw_controller/__init__.py
twgw_controller-2.1.data/data/twgw_controller/api_service.py
twgw_controller-2.1.data/data/twgw_controller/db_manager.py
twgw_controller-2.1.data/data/twgw_controller/gateway.py
twgw_controller-2.1.dist-info/DESCRIPTION.rst
twgw_controller-2.1.dist-info/METADATA
twgw_controller-2.1.dist-info/RECORD
twgw_controller-2.1.dist-info/WHEEL
twgw_controller-2.1.dist-info/entry_points.txt
twgw_controller-2.1.dist-info/metadata.json
twgw_controller-2.1.dist-info/top_level.txt
