Metadata-Version: 2.0
Name: twgw-controller
Version: 2.1
Summary: Controls the Overall Gateway
Home-page: UNKNOWN
Author: Keerthana Jayabal
Author-email: keerthana@trackerwave.com
License: UNKNOWN
Platform: UNKNOWN
Classifier: Development Status :: 1 - Planning
Classifier: Intended Audience :: Developers
Classifier: Programming Language :: Python :: 3
Classifier: Operating System :: Unix
Classifier: Operating System :: MacOS :: MacOS X
Classifier: Operating System :: Microsoft :: Windows
Requires-Python: >=3.7
Requires-Dist: Click
Requires-Dist: termcolor
Requires-Dist: pyinstaller (>=4.3)
Requires-Dist: cython (>=0.29.21)
Requires-Dist: speedtest-cli (>=2.1.3)
Requires-Dist: requests
Requires-Dist: pandas (>=1.1.4)
Requires-Dist: numpy (>=1.19.4)
Requires-Dist: psutil
Requires-Dist: pyfiglet
Requires-Dist: paho-mqtt
Requires-Dist: clickhouse-driver (==0.1.5)
Requires-Dist: setproctitle (>=1.2)
Requires-Dist: pytz
Requires-Dist: pylint
Requires-Dist: getmac
Requires-Dist: packaging
Requires-Dist: cryptography
Requires-Dist: cffi (>=1.14.6)
Requires-Dist: rich
Requires-Dist: futures3
Requires-Dist: pycryptodome
Requires-Dist: pycrypto
Requires-Dist: twgw
